encrypted_config/__init__.py
encrypted_config/__main__.py
encrypted_config/_version.py
encrypted_config/crypto.py
encrypted_config/json_crypto.py
encrypted_config/json_io.py
encrypted_config/json_transform.py
encrypted_config/main.py
encrypted_config/path_tools.py
encrypted_config/py.typed
encrypted_config-0.2.0.dist-info/LICENSE
encrypted_config-0.2.0.dist-info/METADATA
encrypted_config-0.2.0.dist-info/NOTICE
encrypted_config-0.2.0.dist-info/WHEEL
encrypted_config-0.2.0.dist-info/top_level.txt
encrypted_config-0.2.0.dist-info/RECORD
