Metadata-Version: 2.1
Name: encrypted-config
Version: 0.2.0
Summary: Read and write partially encrypted configuration files.
Home-page: https://github.com/mbdevpl/encrypted-config
Download-URL: 
Author: Mateusz Bysiek
Author-email: mateusz.bysiek@gmail.com
Maintainer: Mateusz Bysiek
Maintainer-email: mateusz.bysiek@gmail.com
License: Apache License 2.0
Keywords: config,encryption,rsa,security
Classifier: Development Status :: 1 - Planning
Classifier: Environment :: Console
Classifier: Intended Audience :: Developers
Classifier: License :: OSI Approved :: Apache Software License
Classifier: Natural Language :: English
Classifier: Operating System :: MacOS
Classifier: Operating System :: Microsoft :: Windows
Classifier: Operating System :: POSIX :: Linux
Classifier: Programming Language :: Python :: 3.8
Classifier: Programming Language :: Python :: 3.9
Classifier: Programming Language :: Python :: 3.10
Classifier: Programming Language :: Python :: 3.11
Classifier: Programming Language :: Python :: 3 :: Only
Classifier: Topic :: Communications :: File Sharing
Classifier: Topic :: Security :: Cryptography
Classifier: Topic :: Utilities
Requires-Python: >=3.8
License-File: LICENSE
License-File: NOTICE
Requires-Dist: rsa ~=4.9
Requires-Dist: version-query ~=1.5
